example_package_mhawks/__init__.py
example_package_mhawks/test.py
example_package_mhawks-0.2.dist-info/METADATA
example_package_mhawks-0.2.dist-info/WHEEL
example_package_mhawks-0.2.dist-info/top_level.txt
example_package_mhawks-0.2.dist-info/RECORD
